{
  "updated": "2025-03-01",
  "instruments": [
    { "symbol": "SPY", "name": "SPDR S&P 500" },
    { "symbol": "GLD", "name": "SPDR Gold Shares" },
    { "symbol": "USO", "name": "United States Oil Fund" },
    { "symbol": "EURUSD=X", "name": "EUR/USD" }
  ],
  "windows": ["1M", "3M", "6M", "1Y", "3Y", "5Y", "Max"],
  "strategies": {
    "TREND-02": { "seed": 1421, "trend": 0.16, "vol": 0.18, "drawdown": 0.22 },
    "TREND-05": { "seed": 3322, "trend": 0.12, "vol": 0.14, "drawdown": 0.18 },
    "MR-01": { "seed": 7731, "trend": 0.08, "vol": 0.12, "drawdown": 0.15 },
    "VOL-01": { "seed": 9128, "trend": 0.14, "vol": 0.22, "drawdown": 0.25 },
    "REG-01": { "seed": 5544, "trend": 0.1, "vol": 0.1, "drawdown": 0.12 },
    "MOM-01": { "seed": 8810, "trend": 0.13, "vol": 0.16, "drawdown": 0.2 },
    "TURTLE-01": { "seed": 4157, "trend": 0.15, "vol": 0.19, "drawdown": 0.23 }
  }
}
